tds_flatpath/__init__.py
tds_flatpath/codec.py
tds_flatpath-0.1.0.dist-info/METADATA
tds_flatpath-0.1.0.dist-info/WHEEL
tds_flatpath-0.1.0.dist-info/licenses/LICENSE
tds_flatpath-0.1.0.dist-info/RECORD
