Metadata-Version: 2.4
Name: tds-flatpath
Version: 0.1.0
Summary: Collision-proof, reversible path flattening
Project-URL: Homepage, https://github.com/XRReady/tds-flatpath
Project-URL: Repository, https://github.com/XRReady/tds-flatpath
Project-URL: Issues, https://github.com/XRReady/tds-flatpath/issues
Author-email: Dale Spencer <texasdatasafel@gmail.com>
License: MIT License
License-File: LICENSE
Keywords: encoding,filesystem,flattening,path,reversible
Classifier: License :: OSI Approved :: MIT License
Classifier: Operating System :: OS Independent
Classifier: Programming Language :: Python :: 3
Classifier: Topic :: Software Development :: Libraries
Classifier: Topic :: Utilities
Requires-Python: >=3.8
Provides-Extra: dev
Requires-Dist: black>=24.0; extra == 'dev'
Requires-Dist: mypy>=1.10.0; extra == 'dev'
Requires-Dist: pytest>=8.0; extra == 'dev'
Requires-Dist: ruff>=0.6.0; extra == 'dev'
Provides-Extra: test
Requires-Dist: pytest>=8.0; extra == 'test'
